Workbook

Sheet Conceptos técnicos y REQ.
B5: PALABRA | C5: CONCEPTO TÉCNICO
B6: Python | C6: Lenguaje de programación principal del backend. Es interpretado, de tipado dinámico (con soporte de tipado estático opcional) y tiene una gran cantidad de librerías para web, bases de datos, seguridad y ciencia de datos. Permite desarrollar rápido y mantener el código de forma legible. | E6: Requirimientos | F6: ='REQ. No funcionales backend'!K12+'REQ. No funcionales Database'!K12+'REQ. No funcionales Frontend'!K13+'REQ. funcionales Frontend'!K12+'REQ. funcionales Database'!K12+'REQ. funcionales backend'!K12+Financieras!K12+'Gestion Humana'!K12 -> 1464
B7: FastAPI | C7: FastAPI es un framework de desarrollo web moderno y de alto rendimiento en Python, diseñado para facilitar la creación de APIs de forma rápida y sencilla. Se basa en las sugerencias de tipos estándar de Python y utiliza librerías como Pydantic para la validación y serialización de datos. FastAPI es conocido por su velocidad y facilidad de uso, permitiendo a los desarrolladores crear aplicaciones con menos código y mayor productividad. | E7: Hechos | F7: ='REQ. No funcionales backend'!K13+'REQ. No funcionales Database'!K13+'REQ. No funcionales Frontend'!K14+'REQ. funcionales Frontend'!K13+'REQ. funcionales Database'!K13+'REQ. funcionales backend'!K13+Financieras!K13+'Gestion Humana'!K13 -> 1440
B8: Uvicorn | C8: Servidor ASGI ligero y muy rápido que ejecuta la aplicación FastAPI. Se encarga de recibir las peticiones HTTP, pasarlas a la app y devolver las respuestas. Soporta hot-reload en desarrollo para ver cambios al instante. | E8: Porcentaje | F8: =TEXT(F7/F6,"0.00%") -> 98,36%
B9: SQLAlchemy | C9: Biblioteca usada para conexión y sesiones de base de datos desde el backend. En el proyecto se usa principalmente `Session` y consultas SQL explícitas con `text(...)`, con utilidades ORM puntuales.
B10: Pydantic | C10: Biblioteca Python para validación de datos usando anotaciones de tipos
B11: JWT | C11: JSON Web Tokens son el mecanismo de autenticación. El backend emite tokens firmados con una clave secreta, que el cliente envía en cada petición protegida. python-jose se encarga de firmar, verificar y decodificar estos tokens de forma segura.
B12: bcrypt | C12: Algoritmo de hash para contraseñas. En lugar de guardar las contraseñas en texto plano, se almacena un hash resistente a ataques de fuerza bruta. Bcrypt incluye un “coste” configurable que hace más lento el cálculo del hash (y por tanto más difícil de romper).
B13: python-dotenv | C13: Carga las variables de entorno definidas en un archivo .env (como claves secretas, URLs de base de datos, credenciales de correo). Esto separa la configuración sensible del código fuente y facilita cambiar entornos (desarrollo, pruebas, producción).
B14: SMTP | C14: Conjunto de funciones que usan el protocolo SMTP para enviar correos electrónicos (confirmaciones, recordatorios, contacto). Normalmente se conecta a servidores como Gmail u otros proveedores, autenticándose con usuario y contraseña seguros.
B15: POSTGRESQL | C15: PostgreSQL es un sistema de gestión de base de datos relacional (RDBMS) de código abierto, ampliamente reconocido por su fiabilidad, flexibilidad y capacidad para manejar grandes cantidades de datos. Se considera una de las bases de datos relacionales de código abierto más avanzadas del mundo.
B16: TypeScript | C16: Superconjunto tipado de JavaScript. Añade tipos estáticos opcionales, lo que ayuda a detectar errores en tiempo de compilación, mejorar el autocompletado y hacer el código más mantenible en una base de código grande como este frontend.
B17: React | C17: Es una biblioteca Javascript de código abierto diseñada para crear interfaces de usuario con el objetivo de facilitar el desarrollo de aplicaciones en una sola página.
B18: VITE | C18: Vite es una herramienta de desarrollo para el frontend (parte del sitio web que el usuario ve) que busca acelerar el desarrollo y la construcción de aplicaciones web modernas. Es conocido por su velocidad, tanto en el desarrollo como en la compilación final, y su facilidad de uso.
B19: React Router | C19: Librería de ruteo para React en aplicaciones web. Permite definir rutas (URLs) que cargan páginas o componentes específicos, soporta rutas anidadas, parámetros, protección de rutas (según rol/estado de login) y navegación programática.
B20: TAILWINDCSS | C20: Tailwind CSS es un framework CSS "Utility-first" que proporciona un conjunto de clases de utilidad para diseñar interfaces de usuario de forma rápida y eficiente. En lugar de definir componentes predefinidos como Bootstrap, Tailwind se centra en clases específicas para estilos individuales, como colores, espaciado, fuentes, sombras, etc. Esto permite a los desarrolladores crear diseños personalizados y mantener un código CSS más limpio y optimizado.
... B45: P-XX | C45: Pendiente (Para cualquier Area)

Sheet REQ. funcionales backend
B2: LISTADO DE REQUERIMIENTOS DEL SISTEMA IMPLEMENTACION DEL SOFTWARE DE RESERVAS PARA EVENTOS DE RESTAURANTES EN BUCARAMANGA (RESERVIFY)
B4: SI | C4: Marque con una equis (X) si el sistema cumple con la función descrita
B5: NO | C5: Marque con una equis (X) si el sistema no cumple con la función descrita
B6: ADI | C6: Marque con una equis (X) si el sistema debe adicionar la función descrita | R6: =COUNTA(#REF!,Financieras!C12:C44,#REF!,#REF!,'Gestion Humana'!C12:C23,'REQ. funcionales backend'!#REF!) -> #ERROR!
B7: Observaciones:Espacio para complementar respuestas
E9: Nivel de cumplimiento | H9: OBSERVACIONES
B10: REQUISITOS FUNCIONALES BACKEND | E10: SI | F10: Parcial | G10: NO
B12: 1 | C12: BE-001 – Control de disponibilidad de mesas y prevención de reservas duplicadas | E12: x | J12: Requerimientos | K12: =COUNTA(C12:C178) -> 167
B13: 2 | C13: BE-002 – Autenticación, roles y permisos | E13: x | J13: Hechos | K13: =COUNTA(E12:E178) -> 167
B14: 3 | C14: BE-003 – Gestión de reservas (crear, listar, cancelar, cambiar estado) | E14: x | J14: Porcentaje | K14: =TEXT((K13/K12)*100,"0,00") & "%" -> 100%
B15: 4 | C15: BE-004 – Manejo de estados de reserva | E15: x
B16: 5 | C16: BE-005 – Notificaciones por correo y recordatorios | E16: x
B17: 6 | C17: BE-006 – Reportes y métricas para toma de decisiones | E17: x
B18: 7 | C18: BE-007 – Gestión de responsables y personal administrativo | E18: x
B19: 8 | C19: BE-008 – Comentarios y calificaciones asociadas al restaurante (reseñas de clientes) | E19: x
B20: 9 | C20: BE-009 – Integración con pasarela de pagos externa | E20: x
B21: 10 | C21: BE-010 – Manejo de pagos y facturación | E21: x
B22: 11 | C22: BE-011 – Historial y auditoría de acciones | E22: x
B23: 12 | C23: BE-012 – Gestión de configuración del restaurante (mesas, horarios, capacidad, categoría) | E23: x
B24: 13 | C24: BE-013 – Endpoints JSON claros para operaciones de reserva | E24: x
B25: 14 | C25: BE-014 – Listado y filtrado de reservas para clientes y administradores | E25: x
B26: 15 | C26: BE-015 – Geolocalización de restaurantes para el mapa | E26: x
... B178: 167 | C178: BE-108 – DELETE /calculos_mensuales/borrar_calculo_mensual y GET /calculos_mensuales/listar_calculo_mensual | E178: x

Sheet REQ. No funcionales backend
B2: LISTADO DE REQUERIMIENTOS DEL SISTEMA IMPLEMENTACION DEL SOFTWARE DE RESERVAS PARA EVENTOS DE RESTAURANTES EN BUCARAMANGA (RESERVIFY)
B4: SI | C4: Marque con una equis (X) si el sistema cumple con la función descrita
B5: NO | C5: Marque con una equis (X) si el sistema no cumple con la función descrita
B6: ADI | C6: Marque con una equis (X) si el sistema debe adicionar la función descrita | R6: =COUNTA(#REF!,Financieras!C12:C44,#REF!,#REF!,'Gestion Humana'!C12:C23,'REQ. No funcionales backend'!#REF!) -> #ERROR!
B7: Observaciones:Espacio para complementar respuestas
E9: Nivel de cumplimiento | H9: OBSERVACIONES
B10: REQUISITOS NO FUNCIONALES BACKEND | E10: SI | F10: Parcial | G10: NO
B12: 1 | C12: NFB-001 – Framework y exposición HTTP | E12: x | J12: Requerimientos | K12: =COUNTA(C12:C178) -> 73
B13: 2 | C13: NFB-002 – Configuración externa (.env) | E13: x | J13: Hechos | K13: =COUNTA(E12:E178) -> 57
B14: 3 | C14: NFB-003 – Respuesta JSON y manejo de errores | E14: x | J14: Porcentaje | K14: =TEXT((K13/K12)*100,"0,00") & "%" -> 078%
B15: 4 | C15: NFB-004 – CORS con credenciales | E15: x
B16: 5 | C16: NFB-005 – Preflight OPTIONS | E16: x
B17: 6 | C17: NFB-006 – CORS en respuestas de error | E17: x
B18: 7 | C18: NFB-007 – JWT para rutas protegidas | E18: x
B19: 8 | C19: NFB-008 – Refresh token solo en cookie HttpOnly | E19: x
B20: 9 | C20: NFB-009 – Hash de contraseñas | E20: x
B21: 10 | C21: NFB-010 – Recuperación de contraseña | E21: x
B22: 11 | C22: NFB-011 – Edición de credenciales solo propias | E22: x
B23: 12 | C23: NFB-012 – Motor PostgreSQL | E23: x
B24: 13 | C24: NFB-013 – Consultas parametrizadas | E24: x
B25: 14 | C25: NFB-014 – Auditoría por usuario de aplicación | E25: x
B26: 15 | C26: NFB-015 – Pasarela Wompi | E26: x
... B36: 25 | C36: NFB-025 – Wompi y conectividad de red | E36: x
B37: 26 | C37: NF-001 – Seguridad de datos y control de acceso | F37: x
B38: 27 | C38: NF-002 – Verificación de documentos de soporte de proyecto | G38: x | H38: No aplica (alcance funcional distinto)
B39: 28 | C39: NF-003 – Disponibilidad general del sistema | F39: x
B40: 29 | C40: NF-004 – Escalabilidad para gran cantidad de usuarios y datos | F40: x
B41: 30 | C41: NF-007 – Almacenamiento de registro fotográfico | E41: x
B42: 31 | C42: NF-008 – Capacidad de integrarse con otros sistemas | E42: x
B43: 32 | C43: NF-009 – Tiempo máximo de respuesta de 5 segundos para consultas | F43: x
B44: 33 | C44: NF-010 – Cambio de permisos solo por usuarios autorizados | E44: x
B45: 34 | C45: NF-011 – Disponibilidad del 99,99 % | G45: x | H45: No hecho.
B46: 35 | C46: NF-014 – Capacidad de procesar N transacciones por segundo | G46: x | H46: No hecho.
B47: 36 | C47: NF-015 – Integración con Active Directory y Single Sign-On (SSO) | G47: x | H47: No aplica (alcance funcional distinto)
B48: 37 | C48: NF-016 – Integración con servidores de correo para notificaciones | E48: x
B49: 38 | C49: NF-020 – Integración con servicio de factura electrónica | F49: x
B50: 39 | C50: NF-022 – Interacción con el portal corporativo de la Empresa | G50: x | H50: No aplica (alcance funcional distinto)
B51: 40 | C51: NF-024 – Sistema multicompañía y multisede | G51: x | H51: No aplica (alcance funcional distinto)
B52: 41 | C52: NF-027 – Integración total entre módulos sin redundancia de información | E52: x
B53: 42 | C53: NF-029 – Acceso web para proveedores, órdenes de compra, nómina, etc. | G53: x | H53: No aplica (alcance funcional distinto)
B54: 43 | C54: NF-031 – Parametrización de cantidad, frecuencia y fechas de reportes automáticos | F54: x
B55: 44 | C55: NF-035 – Soporte de estándares de webservices (WSDL, XSLT, SOAP, WS-BPEL, XML) | G55: x | H55: No aplica (stack REST/JSON; un consumidor podría serializar a XML fuera de esta API si lo necesitara).
B56: 45 | C56: NF-042 – Herramienta de integración nativa tipo ESB/colas/batch para ERP corporativo | G56: x | H56: No aplica (alcance e integraciones puntuales)
B57: 46 | C57: NF-045 – Logs consolidados de transacciones por perfil y periodo | E57: x
B58: 47 | C58: NF-047 – Datos personales de usuarios (contacto, email, cargo, etc.) | E58: x
B59: 48 | C59: NF-048 – Restricción de acceso a rutas de backend según rol | E59: x
B60: 49 | C60: NF-049 – Validación de disponibilidad antes de confirmar una reserva | E60: x
B61: 50 | C61: NF-051 – Flujo transaccional integrado entre reserva, factura y pago | E61: x
B62: 51 | C62: NF-055 – Gestión programada de recordatorios de reservas | E62: x
B63: 52 | C63: NF-056 – Almacenamiento y consulta eficiente de correos de negocio | E63: x
B64: 53 | C64: NF-001A – Uso de hashing fuerte para contraseñas de usuarios | E64: x
B65: 54 | C65: NF-001B – Protección de rutas críticas mediante JWT y roles | E65: x
B66: 55 | C66: NF-057 – Uso de bcrypt para hashing de contraseñas | E66: x
B67: 56 | C67: NF-058 – Emisión y validación de JWT (access_token y refresh_token) | E67: x
B68: 57 | C68: NF-059 – Dependencia verificar_token en rutas protegidas | E68: x
... B78: 67 | C78: NF-079 – Backend FastAPI con enrutado por módulos | E78: x
B79: 68 | C79: NF-086 – Rate limit o control en endpoint /contactanos | G79: x | H79: No implementado.
B80: 69 | C80: NF-089 – Password_Reset_Codes para recuperación de contraseña (tabla y lógica si existe) | E80: x
B81: 70 | C81: NF-091 – Cookie HttpOnly para refresh token (no accesible desde JavaScript) | E81: x
B82: 71 | C82: NF-092 – Cookie SameSite=strict para refresh token | E82: x
B83: 72 | C83: NF-093 – Rechazo de tokens revocados en verificar_token | E83: x
B84: 73 | C84: NF-094 – Autorización por recurso: solo editar propias credenciales | E84: x

Sheet REQ. funcionales Frontend
B2: LISTADO DE REQUERIMIENTOS DEL SISTEMA IMPLEMENTACION DEL SOFTWARE DE RESERVAS PARA EVENTOS DE RESTAURANTES EN BUCARAMANGA (RESERVIFY)
B4: SI | C4: Marque con una equis (X) si el sistema cumple con la función descrita
B5: NO | C5: Marque con una equis (X) si el sistema no cumple con la función descrita
B6: ADI | C6: Marque con una equis (X) si el sistema debe adicionar la función descrita
B7: Observaciones:Espacio para complementar respuestas
E9: Nivel de cumplimiento | H9: OBSERVACIONES
B10: REQUISITOS FUNCIONALES FRONTEND | E10: SI | F10: Parcial | G10: NO
B12: 1 | C12: FE-000 – COLOR DE FONDO DE LA PAGINA WEB | E12: x | J12: Requerimientos | K12: =COUNTA(C12:C924) -> 913
B13: 2 | C13: FE-VIG-HOME-01 – Estructura de Home | E13: x | J13: Hechos | K13: =COUNTA(E12:E924) -> 908
B14: 3 | C14: FE-VIG-HOME-02 – Header fijo y navegación | E14: x | J14: Porcentaje | K14: =TEXT((K13/K12)*100,"0,00") & "%" -> 099%
B15: 4 | C15: FE-VIG-HOME-03 – Búsqueda principal por cocina/restaurante | E15: x
B16: 5 | C16: FE-VIG-HOME-04 – Ubicación opcional | E16: x
B17: 6 | C17: FE-VIG-HOME-05 – Carga diferida y rendimiento percibido | E17: x
B18: 7 | C18: FE-VIG-HOME-06 – Tema claro/oscuro por tokens | E18: x
B19: 8 | C19: FE-VIG-SEARCH-01 – Ruta pública `/buscar` (`ROUTES.SEARCH`) | E19: x
B20: 9 | C20: FE-VIG-SEARCH-02 – Parámetros de URL y estado | E20: x
B21: 10 | C21: FE-VIG-SEARCH-03 – Resultados paginados vía API | E21: x
B22: 11 | C22: FE-VIG-SEARCH-04 – Cáscara de página | E22: x
B23: 12 | C23: FE-VIG-LOGIN-01 – Inicio de sesión con correo y contraseña | E23: x
B24: 13 | C24: FE-VIG-LOGIN-02 – Recuperación de contraseña en 3 pasos | E24: x
B25: 14 | C25: FE-VIG-LOGIN-03 – UX de feedback | E25: x
B26: 15 | C26: FE-VIG-LOGIN-04 – Integración de términos y privacidad | E26: x
... B94: 83 | C94: FE-046 – INICIO SESIÓN - modo claro – Separador “O continúa con”: Texto centrado 12px–13px color #8a8a8a. Líneas laterales 1px color #dddddd. | E94: x
B95: 84 | C95: FE-047 – INICIO SESIÓN - modo claro – Botón “Google”: Altura 48px. Fondo #f2f2f2. Borde 1px sólido #dcdcdc. Border-radius 10px. Texto #333333. Icono oficial Google alineado a la izquierda. Hover: #e6e6e6. | G95: x | H95: No implementado / no aplica en el frontend actual.
B96: 85 | C96: FE-048 – INICIO SESIÓN - modo claro – Texto “¿No tienes una cuenta?”: Tamaño 13px–14px. Color #777777 | E96: x
B97: 86 | C97: FE-049 – INICIO SESIÓN - modo claro – Enlace “Regístrate aquí”: Color #ff6b35. Sin fondo. Hover: #e85c2a. | E97: x
B98: 87 | C98: FE-050 – INICIO SESIÓN - modo claro – Texto legal inferior: Tamaño 12px. Color #9a9a9a. Alineación centrada. Espaciado horizontal uniforme entre enlaces. | E98: x
B99: 88 | C99: FE-051 – INICIO SESIÓN - modo claro – Botón modo claro/oscuro (icono sol): Tamaño aproximado 36px x 36px. Fondo neutro claro #f0ebe4. Border-radius 8px. Icono color #ff7a3d. | E99: x
B100: 89 | C100: FE-052 – INICIO SESIÓN - modo claro – Enlace superior “Volver al inicio”: Tamaño 14px. Color #ff7a3d. Sin fondo. Hover con ligera variación de tono. | E100: x
B101: 90 | C101: FE-053 – INICIO SESIÓN - modo claro – Enlace superior “Volver al inicio”: Tamaño 14px. Color #ff7a3d. Sin fondo. Hover con ligera variación de tono. | E101: x
B102: 91 | C102: FE-054 – INICIO SESIÓN - modo oscuro – Fondo general: Degradado radial oscuro centrado en el formulario. Desde negro profundo (#0f0f0f) en los bordes hacia un gris muy oscuro (#1a1a1a – #222222) en la zona central. Debe cubrir 100% del alto y ancho de la pantalla. | E102: x
B103: 92 | C103: FE-055 – INICIO SESIÓN - modo oscuro – Contenedor del formulario: Ancho máximo 420px. Ancho relativo 90% en dispositivos móviles. Padding interno mínimo 32px. Fondo gris muy oscuro (#1c1c1c). Borde 1px sólido rgba(255,255,255,0.05). Border-radius 16px. Sombra exterior 0 10px 30px rgba(0,0,0,0.6). | E103: x
B104: 93 | C104: FE-056 – INICIO SESIÓN - modo oscuro – Icono superior de seguridad: Contenedor 56px x 56px. Border-radius 12px. Degradado diagonal 135° desde #ff7a3d hasta #f4b942. Icono interno en color blanco (#ffffff), centrado. | E104: x
B105: 94 | C105: FE-057 – INICIO SESIÓN - modo oscuro – Título principal “Bienvenido a Reservify”: Fuente sans-serif (Inter/Poppins). Tamaño 36px–42px. Color blanco (#ffffff). Alineación centrada. | E105: x
B106: 95 | C106: FE-058 – INICIO SESIÓN - modo oscuro – Subtítulo “Inicia sesión en tu cuenta”: Tamaño 14px–16px. Color gris claro (#b3b3b3). Centrado. | E106: x
B107: 96 | C107: FE-059 – INICIO SESIÓN - modo oscuro – Subtítulo interno “Iniciar Sesión”: Tamaño 18px–20px.Color blanco (#f5f5f5). | E107: x
... B113: 102 | C113: FE-065 – INICIO SESIÓN - modo oscuro – Separador “O continúa con”: Texto centrado 12px–13px color #8a8a8a. Líneas laterales 1px color rgba(255,255,255,0.1). | E113: x
B114: 103 | C114: FE-066 – INICIO SESIÓN - modo oscuro – Botón “Google”: Altura 48px. Fondo negro sólido (#0d0d0d). Borde 1px sólido rgba(255,255,255,0.08). Border-radius 10px. Texto blanco (#ffffff). Icono oficial Google alineado a la izquierda. Hover: #1a1a1a. | G114: x | H114: No implementado / no aplica en el frontend actual.
B115: 104 | C115: FE-067 – INICIO SESIÓN - modo oscuro – Texto “¿No tienes una cuenta?”: Tamaño 13px–14px. Color gris medio (#9a9a9a). | E115: x
B116: 105 | C116: FE-068 – INICIO SESIÓN - modo oscuro – Enlace “Regístrate aquí”: Color rojo corporativo (#b91c1c). Hover: #991b1b. | E116: x
B117: 106 | C117: FE-069 – INICIO SESIÓN - modo oscuro – Texto legal inferior: Tamaño 12px. Color gris tenue (#7a7a7a). Alineación centrada. Separación uniforme entre enlaces. | E117: x
B118: 107 | C118: FE-070 – INICIO SESIÓN - modo oscuro – Botón modo oscuro (icono luna): Tamaño aproximado 36px x 36px. Fondo negro suave (#111111). Border-radius 8px. Icono color rojo (#b91c1c) o blanco según contraste. | E118: x
B119: 108 | C119: FE-071 – INICIO SESIÓN - modo oscuro – Enlace superior “Volver al inicio”: Tamaño 14px. Color rojo corporativo (#b91c1c). Sin fondo. Hover con ligera variación a #991b1b. | E119: x
B120: 109 | C120: FE-072 – REGISTRO - modo claro – Fondo general: Degradado claro y cálido, transición suave desde beige muy claro (#f5f1ea) en los bordes hacia crema ligeramente más profundo (#ebe4d8 – #e6dccb). Debe cubrir el 100% del alto y ancho de la pantalla. | E120: x
B121: 110 | C121: FE-073 – REGISTRO - modo claro – Contenedor del formulario: Ancho máximo 420px y 90% en móviles. Padding interno 32px. Fondo blanco (#ffffff). Borde 1px rgba. Border-radius 16px. Sombra 0 10px 30px. | E121: x
B122: 111 | C122: FE-074 – REGISTRO - modo claro – Icono superior de seguridad: 56px x 56px. Border-radius 14px. Degradado desde #ff7a3d hasta #7cbf9e. Icono blanco (#ffffff) centrado. Sombra sutil 0 8px 20px. | E122: x
B123: 112 | C123: FE-075 – REGISTRO - modo claro – Título principal “Bienvenido a Reservify”: Fuente sans-serif (Inter/Poppins). Tamaño 36px–42px. Color gris muy oscuro (#222222). Centrado. | E123: x
B124: 113 | C124: FE-076 – REGISTRO - modo claro – Subtítulo “Registra tu cuenta de Reservify”: Tamaño 14px–16px. Color gris medio (#6b7280). Centrado. | E124: x
B125: 114 | C125: FE-077 – REGISTRO - modo claro – Subtítulo interno “Crea tu cuenta”: Tamaño 18px–20px. Color gris oscuro (#2b2b2b). | E125: x
B126: 115 | C126: FE-078 – REGISTRO - modo claro – Texto descriptivo “Ingresa tus datos para crear tu cuenta”: Tamaño 13px–14px. Color gris medio (#8a8a8a). | E126: x
... B132: 121 | C132: FE-084 – REGISTRO - modo claro – Separador “O continúa con”: Texto centrado 12px–13px color #9ca3af. Líneas laterales 1px. | E132: x
B133: 122 | C133: FE-085 – REGISTRO - modo claro – Botón “Google”: Altura 48px. Fondo blanco (#ffffff). Borde 1px. Border-radius 10px. Texto #222222. Hover #f3f4f6. | G133: x | H133: No implementado / no aplica en el frontend actual.
B134: 123 | C134: FE-086 – REGISTRO - modo claro – Texto inferior y enlaces secundarios: Tamaño 12px–14px. Color gris medio (#9ca3af). Enlaces en #ff7a3d con hover #e5672f. | E134: x
B135: 124 | C135: FE-087 – REGISTRO - modo claro – Botón modo oscuro (icono luna): 36px x 36px. Fondo blanco (#ffffff). Borde 1px rgba. Border-radius 8px. Icono gris oscuro (#444444). | E135: x
B136: 125 | C136: FE-088 – REGISTRO - modo claro – Enlace superior “Volver al inicio”: Tamaño 14px. Color #ff7a3d. Hover #e5672f. | E136: x
B137: 126 | C137: FE-089 – REGISTRO - modo oscuro – Fondo general: Fondo oscuro uniforme con ligera variación hacia el centro. Predomina negro profundo (#0f0f0f – #121212) cubriendo el 100% del alto y ancho de la pantalla. | E137: x
B138: 127 | C138: FE-090 – REGISTRO - modo oscuro – Contenedor del formulario: Ancho aproximado 420px, centrado. Fondo gris muy oscuro (#1a1a1a – #1c1c1c). Bordes redondeados (aprox. 16px). Sombra exterior suave que lo separa del fondo. | E138: x
B139: 128 | C139: FE-091 – REGISTRO - modo oscuro – Icono superior de seguridad: Contenedor cuadrado con bordes redondeados (aprox. 12px–14px). Degradado diagonal en tonos naranja. Icono de candado blanco centrado. | E139: x
B140: 129 | C140: FE-092 – REGISTRO - modo oscuro – Título principal “Bienvenido a Reservify”: Tamaño grande (aprox. 36px–42px). Color blanco (#ffffff). Alineación centrada. | E140: x
B141: 130 | C141: FE-093 – REGISTRO - modo oscuro – Subtítulo “Registra tu cuenta de Reservify”: Tamaño pequeño (aprox. 14px–16px). Color gris claro (#b3b3b3). Centrado. | E141: x
B142: 131 | C142: FE-094 – REGISTRO - modo oscuro – Subtítulo interno “Crea tu cuenta”: Tamaño medio (aprox. 18px–20px). Color blanco o gris muy claro. Centrado dentro del formulario. | E142: x
B143: 132 | C143: FE-095 – REGISTRO - modo oscuro – Texto descriptivo “Ingresa tus datos para crear tu cuenta”: Tamaño pequeño (aprox. 13px–14px). Color gris medio. | E143: x
B144: 133 | C144: FE-096 – REGISTRO - modo oscuro – Campo “Correo electrónico”: Altura aproximada 48px. Fondo negro/gris muy oscuro (#111111). Borde sutil más claro que el fondo. Border-radius cercano a 10px. Texto blanco. Placeholder en gris. Icono izquierdo en gris claro. | E144: x
B145: 134 | C145: FE-097 – REGISTRO - modo oscuro – Campo “Contraseña”: Mismos estilos que el campo de correo. Incluye icono izquierdo (candado) y derecho (ojo) en gris claro. | E145: x
... B149: 138 | C149: FE-101 – REGISTRO - modo oscuro – Separador “O continúa con”: Texto pequeño en gris claro, centrado. Líneas horizontales finas a ambos lados en tono gris oscuro. | E149: x
B150: 139 | C150: FE-102 – REGISTRO - modo oscuro – Botón “Google”: Altura aproximada 48px. Fondo negro muy oscuro. Borde fino gris. Border-radius cercano a 10px. Texto blanco. Icono oficial de Google alineado a la izquierda. | G150: x | H150: No implementado / no aplica en el frontend actual.
B151: 140 | C151: FE-103 – REGISTRO - modo oscuro – Enlace superior “Volver al inicio”: Ubicado en la parte superior izquierda. Tamaño pequeño. Color rojo. | E151: x
B152: 141 | C152: FE-104 – REGISTRO - modo oscuro – Botón modo oscuro (icono luna): Ubicado en la parte superior derecha. Forma cuadrada pequeña con bordes redondeados. Fondo oscuro. Icono en tono rojizo. | E152: x
B153: 142 | C153: FE-105 – EMPLEADO (resumen) - modo claro – Fondo general: Área principal en beige claro uniforme. Barra lateral izquierda en gris claro sólido. Cobertura completa del alto visible. | E153: x
B154: 143 | C154: FE-106 – EMPLEADO (resumen) - modo claro – Barra lateral: Fondo gris claro. Separación visual mediante contraste con el fondo principal. Tipografía en color oscuro. | E154: x
B155: 144 | C155: FE-107 – EMPLEADO (resumen) - modo claro – Ítem activo “Resumen”: Fondo naranja sólido (similar a #f97316). Texto blanco (#ffffff). Bordes ligeramente redondeados. | E155: x
B156: 145 | C156: FE-108 – EMPLEADO (resumen) - modo claro – Ítems inactivos (“Mesas”, “Reservas”, “Correos”, “Configuración”): Fondo gris claro o transparente. Texto oscuro. Sin resaltado. | E156: x
B157: 146 | C157: FE-109 – EMPLEADO (resumen) - modo claro – Título “Buenas tardes”: Tamaño grande (aprox. 32px–40px). Color gris muy oscuro o negro suave. Alineación izquierda. | E157: x
B158: 147 | C158: FE-110 – EMPLEADO (resumen) - modo claro – Texto descriptivo: Tamaño menor (14px–16px). Color gris medio para jerarquía visual. | E158: x
B159: 148 | C159: FE-111 – EMPLEADO (resumen) - modo claro – Tarjeta informativa superior: Fondo gris claro. Border-radius 12px–16px. Texto principal en color oscuro. | E159: x
B160: 149 | C160: FE-112 – EMPLEADO (resumen) - modo claro – Etiqueta “Hora actual”: Fondo naranja sólido. Texto blanco. Forma tipo píldora. Tamaño reducido (12px–13px). | E160: x
B161: 150 | C161: FE-113 – EMPLEADO (resumen) - modo claro – Tarjetas de métricas: Fondo gris claro uniforme. Bordes redondeados consistentes (12px–16px). Sombra suave y discreta. | E161: x
B162: 151 | C162: FE-114 – EMPLEADO (resumen) - modo claro – Valores numéricos (0 / $0): Tamaño destacado (20px–24px). Color oscuro de alto contraste. | E162: x
... B755: 744 | C755: FE-707 – Cliente (Home Page Principal) - modo claro – Navegación de carrusel: Botones laterales blancos con flechas azules y puntos de paginación (dots) azules en la base. | E755: x
B756: 745 | C756: FE-708 – Cliente (Home Page Principal) - modo claro – Sección "Restaurantes Destacados": Título principal y subtítulo en gris oscuro; tarjetas con imagen y badge naranja "Disponible hoy".
B757: 746 | C757: FE-709 – Cliente (Home Page Principal) - modo claro – Tarjeta de restaurante: Fondo blanco, nombre en negro bold, descripción en gris, icono de estrella naranja para calificación y dirección con pin gris. | E757: x
B758: 747 | C758: FE-710 – Cliente (Home Page Principal) - modo claro – Botón "Ver disponibilidad": Fondo naranja sólido, texto blanco y border-radius de 8px dentro de la tarjeta de restaurante. | E758: x
B759: 748 | C759: FE-711 – Cliente (Home Page Principal) - modo claro – Sección de beneficios "¿Por qué elegir Reservify?": Bloques con iconos en cajas de colores suaves (rojo, amarillo, verde) y títulos en azul oscuro. | E759: x
B760: 749 | C760: FE-712 – Cliente (Home Page Principal) - modo claro – Banner de descarga (CTA): Degradado de naranja a verde oliva/dorado con texto "¿Listo para tu próxima experiencia culinaria?" en blanco bold. | E760: x
B761: 750 | C761: FE-713 – Cliente (Home Page Principal) - modo claro – Botón "Descargar app": Botón blanco sólido con texto negro y border-radius de 8px, centrado en el banner inferior. | E761: x
B762: 751 | C762: FE-714 – Cliente (Home Page Principal) - modo claro – Pie de página (Footer): Fondo azul oscuro profundo con logo y columnas de navegación; texto de copyright blanco en la base. | E762: x
B763: 752 | C763: FE-715 – Cliente (Aparto descripcion y reserva de restaurante) - modo oscuro – Banner principal (Hero): Imagen a sangre con el nombre del restaurante "prueba" en blanco bold, calificación de estrellas (0.0), categoría y badge rojo "Disponible hoy". | E763: x
B764: 753 | C764: FE-716 – Cliente (Aparto descripcion y reserva de restaurante) - modo oscuro – Barra superior de navegación: Enlace "Volver al inicio" con flecha a la izquierda y logo "Reservify" con selector de modo a la derecha. | E764: x
B765: 754 | C765: FE-717 – Cliente (Aparto descripcion y reserva de restaurante) - modo oscuro – Contenedor de descripción: Recuadro con fondo gris muy oscuro y texto descriptivo en blanco/gris claro. | E765: x
B766: 755 | C766: FE-718 – Cliente (Aparto descripcion y reserva de restaurante) - modo oscuro – Sección "Galería de Imágenes": Título en blanco y grid de imágenes de referencia con bordes redondeados (border-radius 8px). | E766: x
B767: 756 | C767: FE-719 – Cliente (Aparto descripcion y reserva de restaurante) - modo oscuro – Card de Reserva (Sidebar): Fondo gris oscuro con título "Hacer Reserva" e icono de calendario; incluye campos de selección para fecha, hora, comensales y mesa. | E767: x
B768: 757 | C768: FE-720 – Cliente (Aparto descripcion y reserva de restaurante) - modo oscuro – Botón "Hacer Pago de Reserva": Fondo rojo intenso (#991b1b), texto blanco bold e icono de billetera/tarjeta a la izquierda. | E768: x
... B924: 913 | C924: E+C879:C924mpleado (`employee-dashboard.tsx`) – `Sidebar_2`, `Overview_2`, mesas, reservas del día, correos, configuración; balance `EmployeeBalanceService`; cancelación con modal de motivo. | E924: x

Sheet REQ. No funcionales Frontend
B2: LISTADO DE REQUERIMIENTOS DEL SISTEMA IMPLEMENTACION DEL SOFTWARE DE RESERVAS PARA EVENTOS DE RESTAURANTES EN BUCARAMANGA (RESERVIFY)
B4: SI | C4: Marque con una equis (X) si el sistema cumple con la función descrita
B5: NO | C5: Marque con una equis (X) si el sistema no cumple con la función descrita
B6: ADI | C6: Marque con una equis (X) si el sistema debe adicionar la función descrita
B7: Observaciones:Espacio para complementar respuestas
E9: Nivel de cumplimiento | H9: OBSERVACIONES
B10: REQUISITOS NO FUNCIONALES FRONTEND | E10: SI | F10: Parcial | G10: NO
B12: 1 | C12: NFE-001 – Stack de la SPA | E12: x
B13: 2 | C13: NFE-002 – Variables de entorno `VITE_*` | E13: x | J13: Requerimientos | K13: =COUNTA(C12:C178) -> 52
B14: 3 | C14: NFE-003 – Alias de importación "@" | E14: x | J14: Hechos | K14: =COUNTA(E12:E178) -> 50
B15: 4 | C15: NFE-004 – Cliente HTTP y credenciales | E15: x | J15: Porcentaje | K15: =TEXT((K14/K13)*100,"0,00") & "%" -> 096%
B16: 5 | C16: NFE-005 – Renovación proactiva de tokens | E16: x
B17: 6 | C17: NFE-006 – Caché de datos con TanStack Query | E17: x
B18: 7 | C18: NFE-007 – Enrutado del lado del cliente | E18: x
B19: 8 | C19: NFE-008 – Modo estricto de React | E19: x
B20: 9 | C20: NFE-009 – Tailwind CSS y componentes headless | E20: x
B21: 10 | C21: NFE-010 – Tema claro / oscuro / sistema | E21: x
B22: 11 | C22: NFE-011 – Idioma del documento | E22: x
B23: 12 | C23: NFE-012 – División de código en build | E23: x
B24: 13 | C24: NFE-013 – ESLint | E24: x
B25: 14 | C25: NFE-014 – Pruebas automatizadas (unitarias / e2e) | E25: x
B26: 15 | C26: NFE-015 – Límite global de errores de render (Error Boundary) | E26: x
B27: 16 | C27: NFE-016 – Notificaciones en pantalla | E27: x
... B36: 25 | C36: NFE-025 – Cabeceras de seguridad HTTP (CSP, etc.) | E36: x
B37: 26 | C37: NF-013 – Manuales de usuario estructurados | G37: x | H37: No hecho.
B38: 27 | C38: NF-019 – Acceso rápido a menús, funciones y listas | E38: x
B39: 28 | C39: NF-021 – Parametrización en línea (reportes, tablas maestras, ayudas) | E39: x
B40: 29 | C40: NF-025 – Opción de acceso rápido a diferentes aplicaciones o módulos | E40: x
B41: 30 | C41: NF-026 – Definición de menús según perfiles de usuario | E41: x
B42: 31 | C42: NF-028 – Operación vía navegador web (intranet/internet) | E42: x
B43: 32 | C43: NF-030 – Herramientas para toma de decisiones y tableros de control | E43: x
B44: 33 | C44: NF-032 – Exportación de reportes en múltiples formatos | E44: x
B45: 34 | C45: NF-034 – Visualización de reportes en pantalla antes de imprimir | E45: x
B46: 35 | C46: NF-036 – Adaptabilidad avanzada y eliminación automática de código/campos no usados | G46: x | H46: No hecho.
B47: 36 | C47: NF-037 – Reportes parametrizables con validación | E47: x
B48: 37 | C48: NF-043 – Ayuda en línea y tutoriales | E48: x
B49: 38 | C49: NF-044 – Módulo de parametrización de datos maestros y tipos de documentos | E49: x
B50: 39 | C50: NF-046 – Consultas tipo tabla dinámica y exportación de información | E50: x
B51: 40 | C51: NF-050 – Términos y condiciones del servicio | E51: x
B52: 41 | C52: NF-052 – Experiencia de usuario con transiciones y microinteracciones consistentes | E52: x
B53: 42 | C53: NF-053 – Sistema global de notificaciones en la interfaz | E53: x
B54: 43 | C54: NF-054 – Soporte de tema claro/oscuro coherente con el diseño | E54: x
B55: 44 | C55: NF-068 – Uso de Leaflet o similar para mapas | E55: x
B56: 45 | C56: NF-078 – Frontend React con enrutado (React Router) | E56: x
B57: 46 | C57: NF-080 – ToastProvider/ToastContainer como sistema global de notificaciones | E57: x
B58: 47 | C58: NF-081 – Variables CSS para tema claro y oscuro (.dark) | E58: x
... B63: 52 | C63: NF-034A – Vista previa en pantalla de facturas y reportes antes de descarga | E63: x

Sheet REQ. funcionales Database
B2: LISTADO DE REQUERIMIENTOS DEL SISTEMA IMPLEMENTACION DEL SOFTWARE DE RESERVAS PARA EVENTOS DE RESTAURANTES EN BUCARAMANGA (RESERVIFY)
B4: SI | C4: Marque con una equis (X) si el sistema cumple con la función descrita
B5: NO | C5: Marque con una equis (X) si el sistema no cumple con la función descrita
B6: ADI | C6: Marque con una equis (X) si el sistema debe adicionar la función descrita | R6: =COUNTA(#REF!,Financieras!C12:C44,#REF!,#REF!,'Gestion Humana'!C12:C23,'REQ. funcionales Database'!E12:E58) -> 95
B7: Observaciones:Espacio para complementar respuestas
E9: Nivel de cumplimiento | H9: OBSERVACIONES
B10: REQUISITOS FUNCIONALES BASE DE DATOS | E10: SI | F10: Parcial | G10: NO
B12: 1 | C12: DB-001 – Auditoría de tablas del sistema (incluye sesión JWT, correo, reset de contraseña y tablas núcleo) | E12: x | J12: Requerimientos | K12: =COUNTA(C12:C178) -> 126
B13: 2 | C13: DB-002 – Tabla de credenciales | E13: x | J13: Hechos | K13: =COUNTA(E12:E178) -> 126
B14: 3 | C14: DB-003 – Tabla de roles | E14: x | J14: Porcentaje | K14: =TEXT((K13/K12)*100,"0,00") & "%" -> 100%
B15: 4 | C15: DB-004 – Tabla de usuarios (clientes, dueños, empleados) | E15: x
B16: 5 | C16: DB-005 – Tabla de categorías de restaurantes | E16: x
B17: 6 | C17: DB-006 – Tabla de restaurantes | E17: x
B18: 7 | C18: DB-007 – Tabla de mesas | E18: x
B19: 8 | C19: DB-008 – Tabla de encabezado de factura | E19: x
B20: 9 | C20: DB-008A – Tabla de detalle de factura (líneas por encabezado) | E20: x
B21: 10 | C21: DB-008B – Tabla Administrador_restaurante (relación administrador ↔ restaurante) | E21: x
B22: 11 | C22: DB-009 – Tabla de reservas | E22: x
B23: 12 | C23: DB-010 – Tabla de cálculos mensuales | E23: x
B24: 13 | C24: DB-011 – Tabla de comentarios (reseñas por restaurante y cliente) | E24: x
B25: 14 | C25: DB-012 – Integridad referencial y borrado en cascada | E25: x
B26: 15 | C26: DB-013 – Restricciones de formato y unicidad | E26: x
... B137: 126 | C137: DB-116 – Triggers de auditoría en Roles, Categorias, Imagen_referencia_restaurante, jwt_tokens, Password_Reset_Codes, SMTP_config, IMAP_config y Mails | E137: x

Sheet REQ. No funcionales Database
B2: LISTADO DE REQUERIMIENTOS DEL SISTEMA IMPLEMENTACION DEL SOFTWARE DE RESERVAS PARA EVENTOS DE RESTAURANTES EN BUCARAMANGA (RESERVIFY)
B4: SI | C4: Marque con una equis (X) si el sistema cumple con la función descrita
B5: NO | C5: Marque con una equis (X) si el sistema no cumple con la función descrita
B6: ADI | C6: Marque con una equis (X) si el sistema debe adicionar la función descrita | R6: =COUNTA(#REF!,Financieras!C12:C44,#REF!,#REF!,'Gestion Humana'!C12:C23,'REQ. No funcionales Database'!E12:E58) -> 82
B7: Observaciones:Espacio para complementar respuestas
E9: Nivel de cumplimiento | H9: OBSERVACIONES
B10: REQUISITOS NO FUNCIONALES GENERALES | E10: SI | F10: Parcial | G10: NO
B12: 1 | C12: NFD-001 – Motor PostgreSQL | E12: x | J12: Requerimientos | K12: =COUNTA(C12:C178) -> 35
B13: 2 | C13: NFD-002 – Scripts SQL como fuente de verdad | E13: x | J13: Hechos | K13: =COUNTA(E12:E178) -> 34
B14: 3 | C14: NFD-003 – Extensión criptográfica | E14: x | J14: Porcentaje | K14: =TEXT((K13/K12)*100,"0,00") & "%" -> 097%
B15: 4 | C15: NFD-004 – Integridad referencial y reglas en columna | E15: x
B16: 5 | C16: NFD-005 – Índices y unicidad para consultas frecuentes | E16: x
B17: 6 | C17: NFD-006 – Aislamiento por filas (RLS) | E17: x
B18: 7 | C18: NFD-007 – Doble registro de auditoría | E18: x
B19: 8 | C19: NFD-008 – Contexto `app.usuario_id` para auditoría de usuario final | E19: x
B20: 9 | C20: NFD-009 – Copias de seguridad y restauración automatizadas | E20: x
B21: 10 | C21: NFD-010 – Réplicas, conmutación por error y particionamiento | E21: x
B22: 11 | C22: NFD-011 – Codificación de caracteres | E22: x
B23: 12 | C23: NF-005 – Soporte multiusuario | E23: x
B24: 13 | C24: NF-006 – Mantenibilidad y administración de la base de datos | E24: x
B25: 14 | C25: NF-012 – Uso de PostgreSQL como motor de base de datos | E25: x
B26: 15 | C26: NF-017 – Auditoría de cambios en los registros de la base de datos | E26: x
... B29: 18 | C29: NF-033 – Campos definidos por el usuario en archivos maestros y transacciones | E29: x
B30: 19 | C30: NF-038 – Base de datos única de terceros | H30: No aplica
B31: 20 | C31: NF-039 – Restricciones de identificación para terceros (NIT, CC, RC, CE) | E31: x
B32: 21 | C32: NF-040 – Uso de procedimientos almacenados, triggers y vistas | E32: x
B33: 22 | C33: NF-041 – Independencia entre dispositivos de almacenamiento y controladores de software | E33: x
B34: 23 | C34: NF-060 – Triggers de auditoría sobre tablas críticas | E34: x
B35: 24 | C35: NF-061 – Índice idx_mails_credencial_uid en Mails | E35: x
B36: 25 | C36: NF-062 – Índice idx_mails_id_credencial_date en Mails | E36: x
B37: 26 | C37: NF-069 – Tabla jwt_tokens con refresh_token y expiración | E37: x
B38: 27 | C38: NF-072 – Tabla Auditoria con registro JSONB | E38: x
B39: 28 | C39: NF-073 – Función auditoria_insert_trigger para INSERT | E39: x
B40: 29 | C40: NF-074 – Función auditoria_update_trigger para UPDATE | E40: x
B41: 30 | C41: NF-075 – Función auditoria_delete_trigger para DELETE | E41: x
B42: 31 | C42: NF-084 – Trigger validar_admin_tiene_restaurante (nit NOT NULL para administrador) | E42: x
... B46: 35 | C46: NF-007A – Límite de imágenes por restaurante para evitar sobrecarga | E46: x

Sheet Financieras
B2: LISTADO DE REQUERIMIENTOS DEL SISTEMA IMPLEMENTACION DEL SOFTWARE DE RESERVAS PARA EVENTOS DE RESTAURANTES EN BUCARAMANGA (RESERVIFY)
B4: SI | C4: Marque con una equis (X) si el sistema cumple con la función descrita
B5: NO | C5: Marque con una equis (X) si el sistema no cumple con la función descrita
B6: ADI | C6: Marque con una equis (X) si el sistema debe adicionar la función descrita
B7: Observaciones:Espacio para complementar respuestas
E9: Nivel de cumplimiento | H9: OBSERVACIONES
B10: REQUISITOS FUNCIONALES FINANCIERA | E10: SI | F10: Parcial | G10: NO
B12: 1 | C12: FI-001 – Facturación básica por reserva | E12: x | J12: Requerimientos | K12: =COUNTA(C12:C178) -> 50
B13: 2 | C13: FI-002 – Asociación entre reservas, pagos y facturas | E13: x | J13: Hechos | K13: =COUNTA(E12:E178) -> 50
B14: 3 | C14: FI-003 – Integración con pasarela de pagos Wompi | E14: x | J14: Porcentaje | K14: =TEXT((K13/K12)*100,"0,00") & "%" -> 100%
B15: 4 | C15: FI-004 – Seguimiento de ingresos y métricas mensuales | E15: x
B16: 5 | C16: FI-005 – Consultas y reportes de facturación | E16: x
B17: 6 | C17: FI-006 – Auditoría de operaciones financieras | E17: x
B18: 7 | C18: FI-007 – Control de formas de pago y estados de pago | E18: x
B19: 8 | C19: FI-008 – Envío de facturas por correo | E19: x
B20: 9 | C20: FI-009 – Creación conjunta de factura y reserva desde el flujo de reserva | E20: x
B21: 10 | C21: FI-010 – Confirmación financiera de la reserva condicionada a pago aprobado | E21: x
B22: 11 | C22: FI-011 – Persistencia de datos de pasarela de pago para conciliación | E22: x
B23: 12 | C23: FI-012 – Exportación de facturación a CSV y detalle descargable en PDF | E23: x
B24: 13 | C24: FI-001A – Registro obligatorio de forma de pago en cada factura | E24: x
B25: 14 | C25: FI-001B – Registro del valor total de la factura con dos decimales | E25: x
B26: 15 | C26: FI-004A – Consolidación de ingresos por restaurante, mes y año | E26: x
... B61: 50 | C61: FI-045 – Endpoints CRUD /encabezado_factura/ | E61: x

Sheet Gestion Humana
B2: LISTADO DE REQUERIMIENTOS DEL SISTEMA IMPLEMENTACION DEL SOFTWARE DE RESERVAS PARA EVENTOS DE RESTAURANTES EN BUCARAMANGA (RESERVIFY)
B4: SI | C4: Marque con una equis (X) si el sistema cumple con la función descrita
B5: NO | C5: Marque con una equis (X) si el sistema no cumple con la función descrita
B6: ADI | C6: Marque con una equis (X) si el sistema debe adicionar la función descrita
B7: Observaciones:Espacio para complementar respuestas
E9: Nivel de cumplimiento | H9: OBSERVACIONES
B10: REQUISITOS FUNCIONALES ADMINISTRATIVOS | E10: SI | F10: Parcial | G10: NO
B12: 1 | C12: GU-001 – Registro y autenticación de usuarios | E12: x | J12: Requerimientos | K12: =COUNTA(C12:C178) -> 48
B13: 2 | C13: GU-002 – Perfiles de usuario (cliente, dueño, administrador, empleado) | E13: x | J13: Hechos | K13: =COUNTA(E12:E178) -> 48
B14: 3 | C14: GU-003 – Edición y consulta de perfil | E14: x | J14: Porcentaje | K14: =TEXT((K13/K12)*100,"0,00") & "%" -> 100%
B15: 4 | C15: GU-004 – Gestión de personal del restaurante | E15: x
B16: 5 | C16: GU-005 – Control de acceso por rol en el backend | E16: x
B17: 6 | C17: GU-006 – Auditoría de cambios en usuarios y credenciales | E17: x
B18: 7 | C18: GU-007 – Paneles diferenciados según rol (dueño, administrador, empleado); cliente sin dashboard dedicado | E18: x
B19: 8 | C19: GU-008 – Edición de datos personales del cliente desde ProfileModal | E19: x
B20: 9 | C20: GU-009 – Gestión interactiva de empleados y administradores por parte del dueño | E20: x
B21: 10 | C21: GU-001A – Almacenamiento de contraseñas con hash seguro (bcrypt), no en texto plano | E21: x
B22: 11 | C22: GU-002A – Asociación estricta de cada usuario a un rol único | E22: x
B23: 12 | C23: GU-003A – Consulta del perfil del cliente autenticado desde el frontend | E23: x
B24: 13 | C24: GU-004A – Vinculación de empleados a un restaurante específico por NIT | E24: x
B25: 14 | C25: GU-010 – Campo perfil: nombre editable | E25: x
B26: 15 | C26: GU-011 – Campo perfil: apellido editable | E26: x
... B59: 48 | C59: GU-044 – Endpoint GET /data-owner/empleados (listado de empleados para el dueño) | E59: x
